[{"phase": "train", "round": -1, "loss": 3.4241855144500732, "accuracy": 0.0694444477558136}, {"phase": "evaluate", "round": -1, "loss": 3.8032689094543457, "accuracy": 0.05882352963089943}, {"phase": "train", "round": -1, "loss": 3.1580021381378174, "accuracy": 0.3055555522441864}, {"phase": "evaluate", "round": -1, "loss": 2.9407973289489746, "accuracy": 0.7058823704719543}, {"phase": "train", "round": -1, "loss": 1.419709324836731, "accuracy": 0.6875}, {"phase": "evaluate", "round": -1, "loss": 1.5951036214828491, "accuracy": 0.7058823704719543}, {"phase": "train", "round": -1, "loss": 0.5154106616973877, "accuracy": 0.8680555820465088}, {"phase": "evaluate", "round": -1, "loss": 1.225826621055603, "accuracy": 0.7058823704719543}, {"phase": "train", "round": -1, "loss": 0.26994815468788147, "accuracy": 0.9444444179534912}, {"phase": "evaluate", "round": -1, "loss": 1.02843177318573, "accuracy": 0.8235294222831726}, {"phase": "train", "round": -1, "loss": 0.15244120359420776, "accuracy": 0.9791666865348816}, {"phase": "evaluate", "round": -1, "loss": 0.8965928554534912, "accuracy": 0.7058823704719543}, {"phase": "train", "round": -1, "loss": 0.12171260267496109, "accuracy": 0.9930555820465088}, {"phase": "evaluate", "round": -1, "loss": 0.8379093408584595, "accuracy": 0.8235294222831726}, {"phase": "train", "round": -1, "loss": 0.08765261620283127, "accuracy": 0.9930555820465088}, {"phase": "evaluate", "round": -1, "loss": 0.754116415977478, "accuracy": 0.7647058963775635}, {"phase": "train", "round": -1, "loss": 0.07052446156740189, "accuracy": 0.9930555820465088}, {"phase": "evaluate", "round": -1, "loss": 0.6869460344314575, "accuracy": 0.7647058963775635}, {"phase": "train", "round": -1, "loss": 0.05000453069806099, "accuracy": 1.0}, {"phase": "evaluate", "round": -1, "loss": 0.6845393180847168, "accuracy": 0.7647058963775635}, {"phase": "train", "round": -1, "loss": 0.06846210360527039, "accuracy": 0.9930555820465088}, {"phase": "evaluate", "round": -1, "loss": 0.6406413316726685, "accuracy": 0.8235294222831726}, {"phase": "train", "round": -1, "loss": 0.04148353636264801, "accuracy": 1.0}, {"phase": "evaluate", "round": -1, "loss": 0.5926881432533264, "accuracy": 0.8235294222831726}, {"phase": "train", "round": -1, "loss": 0.030681617558002472, "accuracy": 1.0}, {"phase": "evaluate", "round": -1, "loss": 0.6359569430351257, "accuracy": 0.8235294222831726}, {"phase": "train", "round": -1, "loss": 0.033198513090610504, "accuracy": 1.0}, {"phase": "evaluate", "round": -1, "loss": 0.5171594023704529, "accuracy": 0.7647058963775635}, {"phase": "train", "round": -1, "loss": 0.03657570853829384, "accuracy": 0.9930555820465088}, {"phase": "evaluate", "round": -1, "loss": 0.5289272665977478, "accuracy": 0.8235294222831726}, {"phase": "train", "round": -1, "loss": 0.05094575136899948, "accuracy": 0.9930555820465088}, {"phase": "evaluate", "round": -1, "loss": 0.48434555530548096, "accuracy": 0.7647058963775635}, {"phase": "train", "round": -1, "loss": 0.022167228162288666, "accuracy": 1.0}, {"phase": "evaluate", "round": -1, "loss": 0.4882117509841919, "accuracy": 0.7647058963775635}, {"phase": "train", "round": -1, "loss": 0.02413092739880085, "accuracy": 1.0}, {"phase": "evaluate", "round": -1, "loss": 0.429352730512619, "accuracy": 0.8235294222831726}, {"phase": "train", "round": -1, "loss": 0.022343957796692848, "accuracy": 1.0}, {"phase": "evaluate", "round": -1, "loss": 0.43943285942077637, "accuracy": 0.8235294222831726}, {"phase": "train", "round": -1, "loss": 0.013982627540826797, "accuracy": 1.0}, {"phase": "evaluate", "round": -1, "loss": 0.4328768253326416, "accuracy": 0.8235294222831726}, {"phase": "train", "round": -1, "loss": 0.015894075855612755, "accuracy": 1.0}, {"phase": "evaluate", "round": -1, "loss": 0.41727709770202637, "accuracy": 0.8235294222831726}, {"phase": "train", "round": -1, "loss": 0.01151552889496088, "accuracy": 1.0}, {"phase": "evaluate", "round": -1, "loss": 0.40608516335487366, "accuracy": 0.8823529481887817}, {"phase": "train", "round": -1, "loss": 0.013251077383756638, "accuracy": 1.0}, {"phase": "evaluate", "round": -1, "loss": 0.40662074089050293, "accuracy": 0.8235294222831726}, {"phase": "train", "round": -1, "loss": 0.009330387227237225, "accuracy": 1.0}, {"phase": "evaluate", "round": -1, "loss": 0.40186405181884766, "accuracy": 0.8235294222831726}, {"phase": "train", "round": -1, "loss": 0.013568740338087082, "accuracy": 1.0}, {"phase": "evaluate", "round": -1, "loss": 0.3835764229297638, "accuracy": 0.8235294222831726}, {"phase": "train", "round": -1, "loss": 0.011464531533420086, "accuracy": 1.0}, {"phase": "evaluate", "round": -1, "loss": 0.3413507342338562, "accuracy": 0.8823529481887817}, {"phase": "train", "round": -1, "loss": 0.00897286832332611, "accuracy": 1.0}, {"phase": "evaluate", "round": -1, "loss": 0.35345903038978577, "accuracy": 0.8823529481887817}, {"phase": "train", "round": -1, "loss": 0.012818587012588978, "accuracy": 1.0}, {"phase": "evaluate", "round": -1, "loss": 0.3760380744934082, "accuracy": 0.8823529481887817}, {"phase": "train", "round": -1, "loss": 0.009931235574185848, "accuracy": 1.0}, {"phase": "evaluate", "round": -1, "loss": 0.31962618231773376, "accuracy": 0.8823529481887817}, {"phase": "train", "round": -1, "loss": 0.03542916476726532, "accuracy": 0.9930555820465088}, {"phase": "evaluate", "round": -1, "loss": 0.3773568272590637, "accuracy": 0.8823529481887817}, {"phase": "train", "round": -1, "loss": 0.006665188353508711, "accuracy": 1.0}, {"phase": "evaluate", "round": -1, "loss": 0.32063448429107666, "accuracy": 0.8823529481887817}, {"phase": "train", "round": -1, "loss": 0.02460508607327938, "accuracy": 0.9930555820465088}, {"phase": "evaluate", "round": -1, "loss": 0.3411899209022522, "accuracy": 0.8823529481887817}, {"phase": "train", "round": -1, "loss": 0.006167690735310316, "accuracy": 1.0}, {"phase": "evaluate", "round": -1, "loss": 0.3012184798717499, "accuracy": 0.8823529481887817}, {"phase": "train", "round": -1, "loss": 0.008289976045489311, "accuracy": 1.0}, {"phase": "evaluate", "round": -1, "loss": 0.31509068608283997, "accuracy": 0.8823529481887817}, {"phase": "train", "round": -1, "loss": 0.004210466984659433, "accuracy": 1.0}, {"phase": "evaluate", "round": -1, "loss": 0.4053473472595215, "accuracy": 0.8823529481887817}, {"phase": "train", "round": -1, "loss": 0.007133709266781807, "accuracy": 1.0}, {"phase": "evaluate", "round": -1, "loss": 0.34177708625793457, "accuracy": 0.8823529481887817}, {"phase": "train", "round": -1, "loss": 0.006489913910627365, "accuracy": 1.0}, {"phase": "evaluate", "round": -1, "loss": 0.3212853968143463, "accuracy": 0.8823529481887817}, {"phase": "train", "round": -1, "loss": 0.004301329143345356, "accuracy": 1.0}, {"phase": "evaluate", "round": -1, "loss": 0.2852616012096405, "accuracy": 0.8823529481887817}, {"phase": "train", "round": -1, "loss": 0.006678138859570026, "accuracy": 1.0}, {"phase": "evaluate", "round": -1, "loss": 0.3083954453468323, "accuracy": 0.8823529481887817}, {"phase": "train", "round": -1, "loss": 0.003449350129812956, "accuracy": 1.0}, {"phase": "evaluate", "round": -1, "loss": 0.27523720264434814, "accuracy": 0.9411764740943909}, {"phase": "train", "round": -1, "loss": 0.0034005483612418175, "accuracy": 1.0}, {"phase": "evaluate", "round": -1, "loss": 0.2781362533569336, "accuracy": 0.8823529481887817}, {"phase": "train", "round": -1, "loss": 0.0035851048305630684, "accuracy": 1.0}, {"phase": "evaluate", "round": -1, "loss": 0.2914692759513855, "accuracy": 0.8823529481887817}, {"phase": "train", "round": -1, "loss": 0.004448847845196724, "accuracy": 1.0}, {"phase": "evaluate", "round": -1, "loss": 0.2610620856285095, "accuracy": 0.9411764740943909}, {"phase": "train", "round": -1, "loss": 0.003490241477265954, "accuracy": 1.0}, {"phase": "evaluate", "round": -1, "loss": 0.26612377166748047, "accuracy": 0.8823529481887817}, {"phase": "train", "round": -1, "loss": 0.004052671603858471, "accuracy": 1.0}, {"phase": "evaluate", "round": -1, "loss": 0.25848588347435, "accuracy": 0.9411764740943909}, {"phase": "train", "round": -1, "loss": 0.003913764841854572, "accuracy": 1.0}, {"phase": "evaluate", "round": -1, "loss": 0.2186645120382309, "accuracy": 0.9411764740943909}, {"phase": "train", "round": -1, "loss": 0.0034280535764992237, "accuracy": 1.0}, {"phase": "evaluate", "round": -1, "loss": 0.25631779432296753, "accuracy": 0.9411764740943909}, {"phase": "train", "round": -1, "loss": 0.0049574654549360275, "accuracy": 1.0}, {"phase": "evaluate", "round": -1, "loss": 0.24098937213420868, "accuracy": 0.9411764740943909}, {"phase": "train", "round": -1, "loss": 0.0028104132506996393, "accuracy": 1.0}, {"phase": "evaluate", "round": -1, "loss": 0.23762795329093933, "accuracy": 0.9411764740943909}, {"phase": "train", "round": -1, "loss": 0.005041228607296944, "accuracy": 1.0}, {"phase": "evaluate", "round": -1, "loss": 0.28686052560806274, "accuracy": 0.9411764740943909}, {"phase": "train", "round": -1, "loss": 0.012655168771743774, "accuracy": 0.9930555820465088}, {"phase": "evaluate", "round": -1, "loss": 0.23376093804836273, "accuracy": 0.9411764740943909}, {"phase": "train", "round": -1, "loss": 0.0028954893350601196, "accuracy": 1.0}, {"phase": "evaluate", "round": -1, "loss": 0.24855349957942963, "accuracy": 0.9411764740943909}, {"phase": "train", "round": -1, "loss": 0.003393302671611309, "accuracy": 1.0}, {"phase": "evaluate", "round": -1, "loss": 0.26798367500305176, "accuracy": 0.9411764740943909}, {"phase": "train", "round": -1, "loss": 0.003241848200559616, "accuracy": 1.0}, {"phase": "evaluate", "round": -1, "loss": 0.2457738220691681, "accuracy": 0.9411764740943909}, {"phase": "train", "round": -1, "loss": 0.002826008712872863, "accuracy": 1.0}, {"phase": "evaluate", "round": -1, "loss": 0.2735535204410553, "accuracy": 0.9411764740943909}, {"phase": "train", "round": -1, "loss": 0.008066317066550255, "accuracy": 1.0}, {"phase": "evaluate", "round": -1, "loss": 0.2672339975833893, "accuracy": 0.9411764740943909}, {"phase": "train", "round": -1, "loss": 0.0024270061403512955, "accuracy": 1.0}, {"phase": "evaluate", "round": -1, "loss": 0.26845958828926086, "accuracy": 0.9411764740943909}, {"phase": "train", "round": -1, "loss": 0.001959866611286998, "accuracy": 1.0}, {"phase": "evaluate", "round": -1, "loss": 0.2688223123550415, "accuracy": 0.9411764740943909}, {"phase": "train", "round": -1, "loss": 0.0015751556493341923, "accuracy": 1.0}, {"phase": "evaluate", "round": -1, "loss": 0.23905232548713684, "accuracy": 0.9411764740943909}, {"phase": "train", "round": -1, "loss": 0.0017458980437368155, "accuracy": 1.0}, {"phase": "evaluate", "round": -1, "loss": 0.2693311870098114, "accuracy": 0.9411764740943909}, {"phase": "train", "round": -1, "loss": 0.003044138429686427, "accuracy": 1.0}, {"phase": "evaluate", "round": -1, "loss": 0.2532220482826233, "accuracy": 0.9411764740943909}, {"phase": "train", "round": -1, "loss": 0.002146233804523945, "accuracy": 1.0}, {"phase": "evaluate", "round": -1, "loss": 0.24967995285987854, "accuracy": 0.9411764740943909}, {"phase": "train", "round": -1, "loss": 0.0016058147884905338, "accuracy": 1.0}, {"phase": "evaluate", "round": -1, "loss": 0.24774672091007233, "accuracy": 0.9411764740943909}, {"phase": "train", "round": -1, "loss": 0.0012159578036516905, "accuracy": 1.0}, {"phase": "evaluate", "round": -1, "loss": 0.23242513835430145, "accuracy": 0.9411764740943909}, {"phase": "train", "round": -1, "loss": 0.0019370830850675702, "accuracy": 1.0}, {"phase": "evaluate", "round": -1, "loss": 0.24639081954956055, "accuracy": 0.9411764740943909}, {"phase": "train", "round": -1, "loss": 0.0019898575264960527, "accuracy": 1.0}, {"phase": "evaluate", "round": -1, "loss": 0.24968770146369934, "accuracy": 0.9411764740943909}, {"phase": "train", "round": -1, "loss": 0.0014751080889254808, "accuracy": 1.0}, {"phase": "evaluate", "round": -1, "loss": 0.26337915658950806, "accuracy": 0.9411764740943909}, {"phase": "train", "round": -1, "loss": 0.005483346059918404, "accuracy": 1.0}, {"phase": "evaluate", "round": -1, "loss": 0.2532670795917511, "accuracy": 0.8823529481887817}, {"phase": "train", "round": -1, "loss": 0.0024998527951538563, "accuracy": 1.0}, {"phase": "evaluate", "round": -1, "loss": 0.23266279697418213, "accuracy": 0.9411764740943909}, {"phase": "train", "round": -1, "loss": 0.009738871827721596, "accuracy": 0.9930555820465088}, {"phase": "evaluate", "round": -1, "loss": 0.2105107456445694, "accuracy": 0.9411764740943909}, {"phase": "train", "round": -1, "loss": 0.001680282992310822, "accuracy": 1.0}, {"phase": "evaluate", "round": -1, "loss": 0.23661105334758759, "accuracy": 0.9411764740943909}, {"phase": "train", "round": -1, "loss": 0.0016848505474627018, "accuracy": 1.0}, {"phase": "evaluate", "round": -1, "loss": 0.24694569408893585, "accuracy": 0.9411764740943909}, {"phase": "train", "round": -1, "loss": 0.0026600968558341265, "accuracy": 1.0}, {"phase": "evaluate", "round": -1, "loss": 0.23741982877254486, "accuracy": 0.9411764740943909}, {"phase": "train", "round": -1, "loss": 0.001144459005445242, "accuracy": 1.0}, {"phase": "evaluate", "round": -1, "loss": 0.23189303278923035, "accuracy": 0.9411764740943909}, {"phase": "train", "round": -1, "loss": 0.0010772778186947107, "accuracy": 1.0}, {"phase": "evaluate", "round": -1, "loss": 0.24871483445167542, "accuracy": 0.9411764740943909}, {"phase": "train", "round": -1, "loss": 0.001280136057175696, "accuracy": 1.0}, {"phase": "evaluate", "round": -1, "loss": 0.2541341483592987, "accuracy": 0.9411764740943909}, {"phase": "train", "round": -1, "loss": 0.0013187916483730078, "accuracy": 1.0}, {"phase": "evaluate", "round": -1, "loss": 0.256521075963974, "accuracy": 0.9411764740943909}, {"phase": "train", "round": -1, "loss": 0.001496218959800899, "accuracy": 1.0}, {"phase": "evaluate", "round": -1, "loss": 0.24818414449691772, "accuracy": 0.9411764740943909}, {"phase": "train", "round": -1, "loss": 0.0010670828633010387, "accuracy": 1.0}, {"phase": "evaluate", "round": -1, "loss": 0.21119070053100586, "accuracy": 0.9411764740943909}, {"phase": "train", "round": -1, "loss": 0.0010456767631694674, "accuracy": 1.0}, {"phase": "evaluate", "round": -1, "loss": 0.21389295160770416, "accuracy": 0.9411764740943909}]